[
  {
    "name": "Caelia",
    "text": "Splendid! You followed the opening instead of the future you rehearsed.",
    "backgrounds": [],
    "portraits": ["spr_caelia_portrait"],
    "positions": ["center"]
  },
  {
    "name": "Selkie",
    "text": "I want Moon, not a version of her that never surprises me.",
    "backgrounds": [],
    "portraits": ["spr_caelia_portrait", "spr_selkie_portrait"],
    "positions": ["left", "right"]
  },
  {
    "name": "Caelia",
    "text": "Then your navigation is finally honest.",
    "backgrounds": [],
    "portraits": ["spr_caelia_portrait", "spr_selkie_portrait"],
    "positions": ["left", "right"]
  },
  {
    "name": "Selkie",
    "text": "Does Crescent Gate agree?",
    "backgrounds": [],
    "portraits": ["spr_caelia_portrait", "spr_selkie_portrait"],
    "positions": ["left", "right"]
  },
  {
    "name": "Caelia",
    "text": "It does. Go meet her beneath an unwritten sky.",
    "backgrounds": [],
    "portraits": ["spr_caelia_portrait", "spr_selkie_portrait"],
    "positions": ["left", "right"]
  },
  {
    "name": "Selkie",
    "text": "That is the only sky worth sharing.",
    "backgrounds": [],
    "portraits": ["spr_caelia_portrait", "spr_selkie_portrait"],
    "positions": ["left", "right"]
  }
]
